.clang-format
.flake8
.gitignore
.gitmodules
CHANGELOG.md
CODEOWNERS
CODE_OF_CONDUCT
Dockerfile
Dockerfile-cuda
LICENSE
MANIFEST.in
Makefile
README.md
__init__.py
description.txt
packages.txt
setup.py
./src/opendr/__init__.py
./src/opendr/_setup.py
./src/opendr/_version.py
./src/opendr/control/__init__.py
./src/opendr/control/single_demo_grasp/Makefile
./src/opendr/control/single_demo_grasp/README.md
./src/opendr/control/single_demo_grasp/__init__.py
./src/opendr/control/single_demo_grasp/dependencies.ini
./src/opendr/control/single_demo_grasp/install_single_demo_grasp.sh
./src/opendr/control/single_demo_grasp/augmentation/README.md
./src/opendr/control/single_demo_grasp/augmentation/image.png
./src/opendr/control/single_demo_grasp/augmentation/input_example.png
./src/opendr/control/single_demo_grasp/training/__init__.py
./src/opendr/control/single_demo_grasp/training/learner_utils.py
./src/opendr/control/single_demo_grasp/training/single_demo_grasp_learner.py
./src/opendr/engine/__init__.py
./src/opendr/engine/constants.py
./src/opendr/engine/data.py
./src/opendr/engine/datasets.py
./src/opendr/engine/example_learner.py
./src/opendr/engine/learners.py
./src/opendr/engine/target.py
./src/opendr/perception/__init__.py
./src/opendr/planning/__init__.py
./src/opendr/simulation/__init__.py
./src/opendr/utils/__init__.py
./src/opendr_toolkit_single_demo_grasp.egg-info/PKG-INFO
./src/opendr_toolkit_single_demo_grasp.egg-info/SOURCES.txt
./src/opendr_toolkit_single_demo_grasp.egg-info/dependency_links.txt
./src/opendr_toolkit_single_demo_grasp.egg-info/requires.txt
./src/opendr_toolkit_single_demo_grasp.egg-info/top_level.txt
src/opendr/_setup.py
src/opendr/_version.py
src/opendr/control/single_demo_grasp/Makefile
src/opendr/control/single_demo_grasp/README.md
src/opendr/control/single_demo_grasp/__init__.py
src/opendr/control/single_demo_grasp/dependencies.ini
src/opendr/control/single_demo_grasp/install_single_demo_grasp.sh
src/opendr/control/single_demo_grasp/augmentation/README.md
src/opendr/control/single_demo_grasp/augmentation/augmentation_gui.py
src/opendr/control/single_demo_grasp/augmentation/augmentation_utils.py
src/opendr/control/single_demo_grasp/augmentation/image.png
src/opendr/control/single_demo_grasp/augmentation/input_example.png
