Metadata-Version: 1.0
Name: opendr-toolkit-single-demo-grasp
Version: 1.1.1
Summary: Open Deep Learning Toolkit for Robotics (submodule: control/single_demo_grasp)
Home-page: https://github.com/opendr-eu/opendr
Author: OpenDR consortium
Author-email: tefas@csd.auth.gr
License: LICENSE
Platform: UNKNOWN
